nhlapip/__init__.py
nhlapip/__main__ .py
nhlapip/__main__.py
nhlapip/const.py
nhlapip/game.py
nhlapip/get_data.py
nhlapip/md_endpoints.py
nhlapip/minor_endpoints.py
nhlapip/nhl_game.py
nhlapip/nhl_get_data.py
nhlapip/nhl_interactive.py
nhlapip/nhl_md_endpoints.py
nhlapip/nhl_minor_endpoints.py
nhlapip/nhl_player.py
nhlapip/nhl_players.py
nhlapip/nhl_url.py
nhlapip/player.py
nhlapip/schedule.py
nhlapip/standings.py
nhlapip/team.py
nhlapip/tournament.py
nhlapip/url.py
tests/__init__.py
tests/test_const.py
tests/test_game.py
tests/test_md_endpoints.py
tests/test_minor_endpoints.py
tests/test_nhl_game.py
tests/test_nhl_md_endpoints.py
tests/test_nhl_minor_endpoints.py
tests/test_nhl_player.py
tests/test_nhl_players.py
tests/test_nhl_url.py
tests/test_player.py
tests/test_schedule.py
tests/test_standings.py
tests/test_team.py
tests/test_tournament.py
tests/test_url.py
nhlapip-0.0.1.dist-info/LICENSE
nhlapip-0.0.1.dist-info/METADATA
nhlapip-0.0.1.dist-info/WHEEL
nhlapip-0.0.1.dist-info/entry_points.txt
nhlapip-0.0.1.dist-info/top_level.txt
nhlapip-0.0.1.dist-info/RECORD
